MANIFEST.in
setup.py
twitter_data_equipment/Demographics.py
twitter_data_equipment/ForceAtlas2.py
twitter_data_equipment/GraphFactory.py
twitter_data_equipment/Hydration.py
twitter_data_equipment/Processing.py
twitter_data_equipment/Slicing.py
twitter_data_equipment/Summarize.py
twitter_data_equipment/Unshortening.py
twitter_data_equipment/__init__.py
twitter_data_equipment/fa2util.py
twitter_data_equipment.egg-info/PKG-INFO
twitter_data_equipment.egg-info/SOURCES.txt
twitter_data_equipment.egg-info/dependency_links.txt
twitter_data_equipment.egg-info/not-zip-safe
twitter_data_equipment.egg-info/requires.txt
twitter_data_equipment.egg-info/top_level.txt
twitter_data_equipment/data_sheets/population_data.csv
twitter_data_equipment/data_sheets/poverty_data.csv
twitter_data_equipment/data_sheets/race_data.csv